flowtorch/__init__.py
flowtorch/docs.py
flowtorch/lazy.py
flowtorch/utils.py
flowtorch/version.py
flowtorch/bijectors/__init__.py
flowtorch/bijectors/affine.py
flowtorch/bijectors/affine_autoregressive.py
flowtorch/bijectors/affine_fixed.py
flowtorch/bijectors/autoregressive.py
flowtorch/bijectors/base.py
flowtorch/bijectors/bijective_tensor.py
flowtorch/bijectors/compose.py
flowtorch/bijectors/elementwise.py
flowtorch/bijectors/elu.py
flowtorch/bijectors/exp.py
flowtorch/bijectors/fixed.py
flowtorch/bijectors/invert.py
flowtorch/bijectors/leaky_relu.py
flowtorch/bijectors/permute.py
flowtorch/bijectors/power.py
flowtorch/bijectors/sigmoid.py
flowtorch/bijectors/softplus.py
flowtorch/bijectors/spline.py
flowtorch/bijectors/spline_autoregressive.py
flowtorch/bijectors/tanh.py
flowtorch/bijectors/utils.py
flowtorch/bijectors/volume_preserving.py
flowtorch/bijectors/ops/__init__.py
flowtorch/bijectors/ops/affine.py
flowtorch/bijectors/ops/spline.py
flowtorch/distributions/__init__.py
flowtorch/distributions/flow.py
flowtorch/distributions/neals_funnel.py
flowtorch/nn/__init__.py
flowtorch/nn/made.py
flowtorch/ops/__init__.py
flowtorch/parameters/__init__.py
flowtorch/parameters/base.py
flowtorch/parameters/dense_autoregressive.py
flowtorch/parameters/tensor.py
flowtorch-0.8.dist-info/LICENSE.txt
flowtorch-0.8.dist-info/METADATA
flowtorch-0.8.dist-info/WHEEL
flowtorch-0.8.dist-info/top_level.txt
flowtorch-0.8.dist-info/RECORD
