Metadata-Version: 2.1
Name: flowtorch
Version: 0.8
Summary: Normalizing Flows for PyTorch
Home-page: https://flowtorch.ai/users
Author: FlowTorch Development Team
Author-email: info@stefanwebb.me
License: MIT
Project-URL: Documentation, https://flowtorch.ai/users
Project-URL: Source, https://www.github.com/facebookincubator/flowtorch
Keywords: Deep Learning,Bayesian Inference,Statistical Modeling,Variational Inference,PyTorch
Platform: UNKNOWN
Classifier: Development Status :: 3 - Alpha
Classifier: Programming Language :: Python :: 3 :: Only
Classifier: License :: OSI Approved :: MIT License
Classifier: Topic :: Scientific/Engineering
Classifier: Intended Audience :: Science/Research
Classifier: Intended Audience :: Developers
Requires-Python: >=3.7
Provides-Extra: dev
Provides-Extra: test
License-File: LICENSE.txt
